{"cameraMode":{"drawMode":0,"name":"Shaded","section":"Shading Mode"},"sceneLighting":true,"audioPlay":false,"sceneViewState":{"m_AlwaysRefresh":false,"showFog":true,"showSkybox":true,"showFlares":true,"showImageEffects":true,"showParticleSystems":true,"showVisualEffectGraphs":true,"m_FxEnabled":true},"in2DMode":false,"pivot":{"x":544.9172973632813,"y":131.24496459960938,"z":588.1834716796875},"rotation":{"x":-0.2790641486644745,"y":0.6731206774711609,"z":-0.30666598677635195,"w":-0.612511932849884},"size":173.5263214111328,"orthographic":false}